megahal/__init__.py
megahal/megahal.py
megahal/util.py
megahal-0.3.5.data/scripts/megahal
megahal-0.3.5.dist-info/METADATA
megahal-0.3.5.dist-info/WHEEL
megahal-0.3.5.dist-info/top_level.txt
megahal-0.3.5.dist-info/RECORD
